curl2swift/__init__.py
curl2swift/__main__.py
curl2swift/constants.py
curl2swift/generate_output.py
curl2swift/handle_options.py
curl2swift/layers/__init__.py
curl2swift/layers/domain/__init__.py
curl2swift/layers/domain/parameter_type.py
curl2swift/layers/domain/parsing/__init__.py
curl2swift/layers/domain/parsing/get_parser.py
curl2swift/layers/domain/parsing/get_request_name_and_description.py
curl2swift/layers/domain/parsing/get_request_properties.py
curl2swift/layers/domain/parsing/parse_content.py
curl2swift/layers/domain/processing/__init__.py
curl2swift/layers/domain/processing/create_dynamic_values_setter.py
curl2swift/layers/domain/processing/create_dynamic_values_setter_call.py
curl2swift/layers/domain/processing/create_request.py
curl2swift/layers/domain/processing/create_response_model.py
curl2swift/layers/domain/processing/get_response_json.py
curl2swift/layers/domain/processing/prepare_enum_cases.py
curl2swift/layers/domain/processing/process_query_params.py
curl2swift/layers/domain/processing/process_request_template.py
curl2swift/layers/domain/processing/process_test_template.py
curl2swift/layers/presentation/__init__.py
curl2swift/layers/presentation/application.py
curl2swift/layers/presentation/content_presenter.py
curl2swift/layers/presentation/content_view.py
curl2swift/layers/presentation/curl_highlighter.py
curl2swift/layers/presentation/dynamic_parameters_selector_view.py
curl2swift/layers/presentation/main_window.py
curl2swift/layers/presentation/swift_highlighter.py
curl2swift/templates/__init__.py
curl2swift/templates/codable_template.py
curl2swift/templates/request_templates.py
curl2swift/templates/test_template.py
curl2swift/utils/__init__.py
curl2swift/utils/clone_repo.py
curl2swift/utils/dict_to_pretty_string.py
curl2swift/utils/get_default_dynamic_values_dict.py
curl2swift/utils/logger.py
curl2swift/utils/pprint_color.py
curl2swift-0.4.1.dist-info/METADATA
curl2swift-0.4.1.dist-info/WHEEL
curl2swift-0.4.1.dist-info/entry_points.txt
curl2swift-0.4.1.dist-info/top_level.txt
curl2swift-0.4.1.dist-info/RECORD
