Metadata-Version: 2.1
Name: curl2swift
Version: 0.4.1
Summary: Tool for transforming cURL to Swift code.
Home-page: https://github.com/tomnvt/curl2swift
Author: Tom Novotny
Author-email: tom.novota@gmail.com
License: MIT
Platform: UNKNOWN
Classifier: License :: OSI Approved :: MIT License
Classifier: Programming Language :: Python :: 3
Classifier: Programming Language :: Python :: 3.7
Requires-Dist: Pygments
Requires-Dist: requests
Requires-Dist: gitpython
Requires-Dist: QScintilla
Requires-Dist: PyQt5
